{
  "title": "INTERIOR DESIGN: different strokes for different folks",
  "subtitle": "Choose the word that best fits each gap (multiple choice).",
  "passage": "Interior design for the average person has come on leaps and bounds since the advent of home makeover TV shows back in the 1970s, and one thing that these shows have made crystal clear is the distinctive nature of taste. After all, as the saying goes, beauty is in the eye of the beholder and this is definitely the case when it comes to how we decorate our homes.\n\nSome people believe interior design should have a [[1]] look and feel, considering embellishments, such as cushions to be unnecessary as they detract from purpose and function. These people tend to splash out on a few timeless pieces of furniture from [[2]] designers or shops, rather than have lots of bits and pieces at a lower price point. They would choose [[3]] elegance over anything that could be considered [[4]] or showy. This [[5]] approach is synonymous with contemporary design. Replete with sleek fixtures and fittings, many [[6]] modern offices have adopted this look in order to denote a level of success, sophistication and quality.\n\nNot everyone is into this however, and for the more [[7]] amongst us, when it comes to curtains, cushions, rugs and ornaments, the more [[8]] the approach, the better. These people enjoy being surrounded by items that will stand out and take centre stage. They are likely to choose [[9]], eye-catching colours for the walls to create a bold contrast with those of the furnishings.\n\nThen, there are those who love an eclectic, vintage look. These people are often to be found at flea markets looking for items to collect that reflect the motifs and styles of bygone eras, from wallpaper and colour schemes to furniture and accessories. Take the 1980s, for instance, when bright, [[10]] colours were all the rage. While this style may still be loved by fans of vintage, others consider it to be [[11]] and a sign of poor taste.\n\nAt the end of the day, whatever your style preference, be it the wild and the wacky or something altogether more muted and [[12]], the best advice is probably to embrace it and enjoy it.",
  "example": null,
  "items": [
    { "options": ["garish", "utilitarian", "whimsical", "minimalistic"], "correctIndex": 1 },
    { "options": ["renowned", "vulgar", "unassuming", "garish"], "correctIndex": 0 },
    { "options": ["imposing", "understated", "vulgar", "garish"], "correctIndex": 1 },
    { "options": ["minimalistic", "ostentatious", "utilitarian", "whimsical"], "correctIndex": 1 },
    { "options": ["flamboyant", "minimalistic", "renowned", "utilitarian"], "correctIndex": 1 },
    { "options": ["garish", "imposing", "swanky", "unassuming"], "correctIndex": 2 },
    { "options": ["flamboyant", "imposing", "utilitarian", "understated"], "correctIndex": 0 },
    { "options": ["unassuming", "utilitarian", "whimsical", "garish"], "correctIndex": 2 },
    { "options": ["imposing", "minimalistic", "unassuming", "understated"], "correctIndex": 0 },
    { "options": ["garish", "minimalistic", "swanky", "unassuming"], "correctIndex": 0 },
    { "options": ["renowned", "vulgar", "understated", "utilitarian"], "correctIndex": 1 },
    { "options": ["garish", "renowned", "unassuming", "whimsical"], "correctIndex": 2 }
  ]
}
